MANIFEST.in
setup.py
WindAdapter/__init__.py
WindAdapter/api.py
WindAdapter/custom_logger.py
WindAdapter/data_dict.csv
WindAdapter/data_provider.py
WindAdapter/enums.py
WindAdapter/factor_loader.py
WindAdapter/helper.py
WindAdapter/utils.py
WindAdapter.egg-info/PKG-INFO
WindAdapter.egg-info/SOURCES.txt
WindAdapter.egg-info/dependency_links.txt
WindAdapter.egg-info/requires.txt
WindAdapter.egg-info/top_level.txt
WindAdapter/tests/__init__.py
WindAdapter/tests/test_api.py
WindAdapter/tests/test_suite.py
WindAdapter/tests/test_windpy.py
requirements/py2.txt
requirements/py3.txt