Metadata-Version: 1.1
Name: WindAdapter
Version: 0.3.9
Summary: Windpy data adapter
Home-page: https://github.com/iLampard/WindAdapter
Author: iLampard, RoxanneYang, bella21
Author-email: UNKNOWN
License: UNKNOWN
Platform: UNKNOWN
Classifier: Programming Language :: Python
Classifier: Programming Language :: Python :: 2.7
Classifier: Programming Language :: Python :: 3.5
Classifier: Programming Language :: Python :: 3.6
